gcli/__init__.py
gcli/cli.py
gcli/clone.py
gcli/config.py
gcli/gitlab_python.py
gcli/pull_repos.py
gitcli-0.0.1.data/scripts/cli.py
gitcli-0.0.1.dist-info/LICENSE
gitcli-0.0.1.dist-info/METADATA
gitcli-0.0.1.dist-info/WHEEL
gitcli-0.0.1.dist-info/entry_points.txt
gitcli-0.0.1.dist-info/top_level.txt
gitcli-0.0.1.dist-info/RECORD
